autoPyTorch/__init__.py
autoPyTorch/__version__.py
autoPyTorch/constants.py
autoPyTorch/py.typed
autoPyTorch/api/__init__.py
autoPyTorch/api/base_task.py
autoPyTorch/api/tabular_classification.py
autoPyTorch/api/tabular_regression.py
autoPyTorch/api/time_series_forecasting.py
autoPyTorch/automl_common/__init__.py
autoPyTorch/automl_common/setup.py
autoPyTorch/automl_common/common/__init__.py
autoPyTorch/automl_common/common/ensemble_building/__init__.py
autoPyTorch/automl_common/common/ensemble_building/abstract_ensemble.py
autoPyTorch/automl_common/common/utils/__init__.py
autoPyTorch/automl_common/common/utils/backend.py
autoPyTorch/automl_common/common/utils/logging_.py
autoPyTorch/configs/__init__.py
autoPyTorch/configs/default_pipeline_options.json
autoPyTorch/configs/forecasting_init_cfgs.json
autoPyTorch/configs/greedy_portfolio.json
autoPyTorch/data/__init__.py
autoPyTorch/data/base_feature_validator.py
autoPyTorch/data/base_target_validator.py
autoPyTorch/data/base_validator.py
autoPyTorch/data/tabular_feature_validator.py
autoPyTorch/data/tabular_target_validator.py
autoPyTorch/data/tabular_validator.py
autoPyTorch/data/time_series_feature_validator.py
autoPyTorch/data/time_series_forecasting_validator.py
autoPyTorch/data/time_series_target_validator.py
autoPyTorch/data/utils.py
autoPyTorch/datasets/__init__.py
autoPyTorch/datasets/base_dataset.py
autoPyTorch/datasets/image_dataset.py
autoPyTorch/datasets/resampling_strategy.py
autoPyTorch/datasets/tabular_dataset.py
autoPyTorch/datasets/time_series_dataset.py
autoPyTorch/ensemble/__init__.py
autoPyTorch/ensemble/abstract_ensemble.py
autoPyTorch/ensemble/ensemble_builder.py
autoPyTorch/ensemble/ensemble_selection.py
autoPyTorch/ensemble/singlebest_ensemble.py
autoPyTorch/evaluation/__init__.py
autoPyTorch/evaluation/abstract_evaluator.py
autoPyTorch/evaluation/tae.py
autoPyTorch/evaluation/test_evaluator.py
autoPyTorch/evaluation/time_series_forecasting_train_evaluator.py
autoPyTorch-0.2.1.dist-info/LICENSE
autoPyTorch-0.2.1.dist-info/METADATA
autoPyTorch-0.2.1.dist-info/WHEEL
autoPyTorch-0.2.1.dist-info/dependency_links.txt
autoPyTorch-0.2.1.dist-info/top_level.txt
autoPyTorch-0.2.1.dist-info/RECORD
