Metadata-Version: 2.1
Name: autoPyTorch
Version: 0.2.1
Summary: Auto-PyTorch searches neural architectures using smac
Home-page: https://github.com/automl/Auto-PyTorch
Author: AutoML Freiburg
Author-email: eddiebergmanhs@gmail.com
License: 3-clause BSD
Keywords: machine learning algorithm configuration hyperparameteroptimization tuning neural architecture deep learning
Platform: Linux
Classifier: Development Status :: 3 - Alpha
Classifier: Topic :: Utilities
Classifier: Topic :: Scientific/Engineering
Classifier: Topic :: Scientific/Engineering :: Artificial Intelligence
Classifier: Programming Language :: Python :: 3.7
Classifier: Programming Language :: Python :: 3.8
Classifier: Programming Language :: Python :: 3.9
Classifier: License :: OSI Approved :: BSD License
Requires-Python: >=3.7
License-File: LICENSE
Requires-Dist: pandas
Requires-Dist: torch (>=1.10.1)
Requires-Dist: torchvision
Requires-Dist: tensorboard
Requires-Dist: scikit-learn (<0.25.0,>=0.24.0)
Requires-Dist: numpy
Requires-Dist: scipy (>=1.7)
Requires-Dist: lockfile
Requires-Dist: imgaug (>=0.4.0)
Requires-Dist: ConfigSpace (>=0.5.0)
Requires-Dist: pynisher (>=0.6.3)
Requires-Dist: pyrfr (<0.9,>=0.7)
Requires-Dist: smac (>=1.2)
Requires-Dist: dask
Requires-Dist: distributed (>=2.2.0)
Requires-Dist: catboost
Requires-Dist: lightgbm
Requires-Dist: flaky
Requires-Dist: tabulate
Provides-Extra: docs
Requires-Dist: sphinx ; extra == 'docs'
Requires-Dist: sphinx-gallery ; extra == 'docs'
Requires-Dist: sphinx-bootstrap-theme ; extra == 'docs'
Requires-Dist: numpydoc ; extra == 'docs'
Provides-Extra: examples
Requires-Dist: matplotlib ; extra == 'examples'
Requires-Dist: jupyter ; extra == 'examples'
Requires-Dist: notebook ; extra == 'examples'
Requires-Dist: seaborn ; extra == 'examples'
Requires-Dist: openml ; extra == 'examples'
Provides-Extra: forecasting
Requires-Dist: gluonts (>=0.10.0) ; extra == 'forecasting'
Requires-Dist: sktime ; extra == 'forecasting'
Requires-Dist: pytorch-forecasting ; extra == 'forecasting'
Provides-Extra: test
Requires-Dist: matplotlib ; extra == 'test'
Requires-Dist: pytest ; extra == 'test'
Requires-Dist: pytest-xdist ; extra == 'test'
Requires-Dist: pytest-timeout ; extra == 'test'
Requires-Dist: flaky ; extra == 'test'
Requires-Dist: pyarrow ; extra == 'test'
Requires-Dist: pre-commit ; extra == 'test'
Requires-Dist: pytest-cov ; extra == 'test'
Requires-Dist: pytest-forked ; extra == 'test'
Requires-Dist: pytest-subtests ; extra == 'test'
Requires-Dist: codecov ; extra == 'test'
Requires-Dist: pep8 ; extra == 'test'
Requires-Dist: mypy ; extra == 'test'
Requires-Dist: openml ; extra == 'test'
Requires-Dist: emcee ; extra == 'test'
Requires-Dist: scikit-optimize ; extra == 'test'
Requires-Dist: pyDOE ; extra == 'test'
